ipyslides/__init__.py
ipyslides/__version__.py
ipyslides/_demo.py
ipyslides/_interact.py
ipyslides/core.py
ipyslides/dashlab.py
ipyslides/formatters.py
ipyslides/interaction.py
ipyslides/source.py
ipyslides/utils.py
ipyslides/writer.py
ipyslides/xmd.py
ipyslides/_base/__init__.py
ipyslides/_base/_layout_css.py
ipyslides/_base/_syntax.py
ipyslides/_base/_widgets.py
ipyslides/_base/base.py
ipyslides/_base/export_html.py
ipyslides/_base/export_template.py
ipyslides/_base/icons.py
ipyslides/_base/intro.py
ipyslides/_base/navigation.py
ipyslides/_base/notes.py
ipyslides/_base/screenshot.py
ipyslides/_base/scripts.py
ipyslides/_base/settings.py
ipyslides/_base/slide.py
ipyslides/_base/styles.py
ipyslides/_base/widgets.py
ipyslides/_base/js/animator.js
ipyslides/_base/js/interaction.js
ipyslides/_base/js/notes.js
ipyslides/_base/static/interaction.css
ipyslides/_base/static/interaction.js
ipyslides/_base/static/laser.css
ipyslides/_base/static/laser.js
ipyslides/_base/static/notes.js
ipyslides-6.8.2.dist-info/LICENSE
ipyslides-6.8.2.dist-info/METADATA
ipyslides-6.8.2.dist-info/WHEEL
ipyslides-6.8.2.dist-info/top_level.txt
ipyslides-6.8.2.dist-info/RECORD
