Metadata-Version: 2.1
Name: ipyslides
Version: 6.8.2
Summary: Live rich content slides in jupyter notebook
Home-page: https://github.com/asaboor-gh/ipyslides
Author: Abdul Saboor
Author-email: asaboor.my@outlook.com
License: MIT
Project-URL: Bug Tracker, https://github.com/asaboor-gh/ipyslides/issues
Keywords: Jupyter,Widgets,IPython
Platform: UNKNOWN
Classifier: License :: OSI Approved :: MIT License
Classifier: Programming Language :: Python :: 3
Classifier: Operating System :: OS Independent
Requires-Python: >=3.9
License-File: LICENSE
Requires-Dist: markdown
Requires-Dist: ipywidgets>=8.0.4
Requires-Dist: pillow>=9.3.0
Requires-Dist: anywidget==0.9.13
Requires-Dist: tldraw==2.2.4
Requires-Dist: dashlab
Provides-Extra: extra
Requires-Dist: jupyterlab>=3.5.2; extra == "extra"
Requires-Dist: ipython>=9.0; extra == "extra"
